snap_plugin/__init__.py
snap_plugin/v1/__init__.py
snap_plugin/v1/_version.py
snap_plugin/v1/bool_policy.py
snap_plugin/v1/collect_arg.py
snap_plugin/v1/collector.py
snap_plugin/v1/collector_proxy.py
snap_plugin/v1/config_map.py
snap_plugin/v1/config_policy.py
snap_plugin/v1/float_policy.py
snap_plugin/v1/get_metrictypes_arg.py
snap_plugin/v1/integer_policy.py
snap_plugin/v1/metric.py
snap_plugin/v1/metrics_arg.py
snap_plugin/v1/namespace.py
snap_plugin/v1/namespace_element.py
snap_plugin/v1/plugin.py
snap_plugin/v1/plugin_pb2.py
snap_plugin/v1/plugin_proxy.py
snap_plugin/v1/processor.py
snap_plugin/v1/processor_proxy.py
snap_plugin/v1/pub_proc_arg.py
snap_plugin/v1/publisher.py
snap_plugin/v1/publisher_proxy.py
snap_plugin/v1/stream_collector.py
snap_plugin/v1/stream_collector_proxy.py
snap_plugin/v1/string_policy.py
snap_plugin/v1/timestamp.py
snap_plugin_lib_py-1.3.1.dist-info/DESCRIPTION.rst
snap_plugin_lib_py-1.3.1.dist-info/METADATA
snap_plugin_lib_py-1.3.1.dist-info/RECORD
snap_plugin_lib_py-1.3.1.dist-info/WHEEL
snap_plugin_lib_py-1.3.1.dist-info/metadata.json
snap_plugin_lib_py-1.3.1.dist-info/top_level.txt
