Metadata-Version: 2.0
Name: snap-plugin-lib-py
Version: 1.3.1
Summary: This is a lib for creating plugins for the Snap telemetry framework.
Home-page: http://github.com/intelsdi-x/snap-plugin-lib-py
Author: Joel Cooklin
Author-email: joel.cooklin@gmail.com
License: Apache 2.0
Keywords: snap telemetry plugin plugins metrics
Platform: UNKNOWN
Requires-Dist: future (>=0.16.0)
Requires-Dist: futures (>=3.0.5)
Requires-Dist: grpcio (>=1.1.3,<2)
Requires-Dist: protobuf (>=3.2.0,<4)
